wemedia/__init__.py
wemedia/skeleton.py
wemedia-0.1.0.dist-info/AUTHORS.rst
wemedia-0.1.0.dist-info/LICENSE.txt
wemedia-0.1.0.dist-info/METADATA
wemedia-0.1.0.dist-info/WHEEL
wemedia-0.1.0.dist-info/top_level.txt
wemedia-0.1.0.dist-info/RECORD
