Metadata-Version: 2.2
Name: wemedia
Version: 0.1.0
Summary: Add a short description here!
Home-page: https://github.com/pyscaffold/pyscaffold/
Author: Walter Ye
Author-email: Walter Ye <hupeng.net@hotmail.com>
License: The MIT License (MIT)
Platform: any
Classifier: Programming Language :: Python :: 3
Classifier: Operating System :: OS Independent
Classifier: License :: OSI Approved :: MIT License
Requires-Python: >=3.12
License-File: LICENSE.txt
License-File: AUTHORS.rst
